kango/__init__.py
kango/db.py
kango/dict_mutator.py
kango/dict_query.py
kango/lib.py
kango/lib_collection.py
kango/lib_xql.py
kango-0.2.0.dist-info/LICENSE
kango-0.2.0.dist-info/METADATA
kango-0.2.0.dist-info/WHEEL
kango-0.2.0.dist-info/top_level.txt
kango-0.2.0.dist-info/RECORD
