Metadata-Version: 2.1
Name: kango
Version: 0.2.0
Summary: kango 
Home-page: https://github.com/mardix/kango
Author: Mardix
Author-email: mardix@blackdevhub.io
Classifier: Programming Language :: Python :: 3
Classifier: License :: OSI Approved :: MIT License
Classifier: Topic :: Database
Requires-Python: >=3.8.0
License-File: LICENSE
Requires-Dist: flask
Requires-Dist: slugify
Requires-Dist: arrow
Requires-Dist: ulid
Requires-Dist: python-arango
